biosequtils/__init__.py
biosequtils/constants.py
biosequtils/dir.py
biosequtils/file.py
biosequtils/handle_json.py
biosequtils/iterator.py
biosequtils/jtxt.py
biosequtils/key_value.py
biosequtils/threading.py
biosequtils-1.0.3.dist-info/LICENSE
biosequtils-1.0.3.dist-info/METADATA
biosequtils-1.0.3.dist-info/WHEEL
biosequtils-1.0.3.dist-info/top_level.txt
biosequtils-1.0.3.dist-info/RECORD
