Metadata-Version: 2.1
Name: biosequtils
Version: 1.0.3
Summary: Provide methods on hand for bioinformatics coding work
Home-page: https://github.com/Tiezhengyuan/bio_utils
Author: Tiezheng Yuan
Author-email: tiezhengyuan@hotmail.com
Keywords: pypi,cicd,python
Classifier: Development Status :: 1 - Planning
Classifier: Intended Audience :: Developers
Classifier: Programming Language :: Python :: 3
Classifier: Operating System :: Unix
Classifier: Operating System :: MacOS :: MacOS X
Classifier: Operating System :: Microsoft :: Windows
License-File: LICENSE
Requires-Dist: Bio
Requires-Dist: numpy
Requires-Dist: pandas
